<?xml version="1.0" encoding="utf-8"?>
<ImportExportXml version="9.1.0.643" SolutionPackageVersion="9.1" languagecode="1033" generatedBy="CrmLive" xmlns:xsi="http://www.w3.org/2001/XMLSchema-instance">
  <SolutionManifest>
    <!-- Unique Name of Cds Solution-->
    <UniqueName>EPRPCFSubmissions</UniqueName>
    <LocalizedNames>
      <!-- Localized Solution Name in language code -->
      <LocalizedName description="PCF Power Controls" languagecode="1033" />
    </LocalizedNames>
    <Descriptions />
    <Version>0.1.1</Version>
    <!-- Solution Package Type: Unmanaged(0)/Managed(1)/Both(2)-->
    <Managed>2</Managed>
    <Publisher>
      <!-- Unique Publisher Name of Cds Solution -->
      <UniqueName>EswarPrakash</UniqueName>
      <LocalizedNames>
        <!-- Localized Cds Publisher Name in language code-->
        <LocalizedName description="Eswar Prakash" languagecode="1033" />
      </LocalizedNames>
      <Descriptions>
        <!-- Description of Cds Publisher in language code -->
        <Description description="A collection PCF controls submitted to pcf.gallery by the author" languagecode="1033" />
      </Descriptions>
      <EMailAddress xsi:nil="true">hello@eswarprakash.com</EMailAddress>
      <SupportingWebsiteUrl xsi:nil="true">https://github.com/eswarpr/pcfgallery-submissions</SupportingWebsiteUrl>
      <!-- Customization Prefix for the Cds Publisher-->
      <CustomizationPrefix>epr</CustomizationPrefix>
      <!-- Derived Option Value Prefix for the Customization Prefix of Cds Publisher -->
      <CustomizationOptionValuePrefix>42411</CustomizationOptionValuePrefix>
      <Addresses></Addresses>
    </Publisher>
    <RootComponents />
    <MissingDependencies />
  </SolutionManifest>
</ImportExportXml>